{"id":8148,"title":"中共國防預算統計","資料集描述":"中共國防預算統計","主要欄位說明":"年份、國防預算總額、國防預算增長％、財務總支出、佔財務總支出％、國內生產總占國內生產總額％\t折合億美元\t預算與決算總額","資料資源":[{"type":"csv","url":"http://data.gov.tw/iisi/logaccess/2369?dataUrl=http://www.mnd.gov.tw/UserFiles/File/中共2000年至2011年國防預算統計--100年.csv&ndctype=CSV&ndcnid=8148"}],"資料集類型":"原始資料","資料集提供機關名稱":"國防部","資料量":"約12筆","更新頻率":"2年","授權方式":"政府資料開放授權條款-第1版","授權說明網址":"http://data.gov.tw/license","計費方式":"免費","資料集提供機關聯絡人":"許先生","資料集提供機關聯絡人電話":"02-23313523","發布時間":"103年05月20日","資料集標籤":"中共國防預算統計","下載次數":235}