{"id":19033,"title":"經濟部中部辦公室_公務預算會計月報","資料集描述":"經費類、歲入類會計報告","主要欄位說明":"經濟部公務預算會計月報下載檔案","資料資源":[{"type":"xml","url":"http://data.gov.tw/iisi/logaccess/49451?dataUrl=http://www.cto.moea.gov.tw/OD/105會計月報.rar&ndctype=XML&ndcnid=19033"},{"type":"xml","url":"http://data.gov.tw/iisi/logaccess/13881?dataUrl=http://www.cto.moea.gov.tw/OD/104會計月報.rar&ndctype=XML&ndcnid=19033"}],"資料集類型":"其他","資料集提供機關名稱":"經濟部","資料量":"約864筆","更新頻率":"每月","授權方式":"政府資料開放授權條款-第1版","授權說明網址":"http://data.gov.tw/license","計費方式":"免費","資料集提供機關聯絡人":"吳小姐","資料集提供機關聯絡人電話":"049-2359171#8812","發布時間":"104年08月14日","開始收錄日期":"104年01月01日","結束收錄日期":"105年02月25日","資料集語系":"中文","資料集標籤":"會計月報","下載次數":85}